LICENSE
README.rst
setup.py
nFunNN/__init__.py
nFunNN/main.py
nFunNN.egg-info/PKG-INFO
nFunNN.egg-info/SOURCES.txt
nFunNN.egg-info/dependency_links.txt
nFunNN.egg-info/requires.txt
nFunNN.egg-info/top_level.txt