Metadata-Version: 2.1
Name: nFunNN
Version: 0.0.1
Summary: Nonlinear Functional Principal Component Analysis Using Neural Networks
Home-page: 
Author: Rou Zhong
Author-email: zhong_rou@163.com
Classifier: Programming Language :: Python :: 3
Classifier: License :: OSI Approved :: MIT License
Classifier: Operating System :: OS Independent
Requires-Python: >=3.8
License-File: LICENSE
